{
  "song": "Près de ma rivière",
  "artist": "Robert Cogoi",
  "country": "Belgium",
  "year": "1964",
  "lyrics": "\n\nFrench\nTranslation\n\n\n\nFrench\nPrès de ma rivière aux reflets d’argent\nEntre ciel et terre, nous, on s’aimait tant\nDans l’herbe légère volaient nos serments\nPrès de ma rivière aux poissons d’argent\nLà, le monde était si loin\nLà, il n’y avait plus rien\nRien que mes yeux dans tes yeux\nRien, rien que nous deux\nPrès de ma rivière aux reflets d’argent\nEntre ciel et terre, nous, on s’aimait tant\nCoule la rivière et coule le temps\nTriste et solitaire, je viens maintenant\nPrès de ma rivière, où l’on s’aimait tant\nPrès de ma rivière, où l’on s’aimait tant\n\n"
}
