{
  "song": "Ela Ela (Come Baby)",
  "artist": "Constantinos Christoforou",
  "country": "Cyprus",
  "year": "2005",
  "lyrics": "\n\n(Ela, ela, ela, ela, ela, la…)\n(Ela, ela, ela, ela, ela, la…)\nYou’re there, I’m here\nNo need to fear\nFeel around me the desire\nSearch my body, reach the fire\nJust cross the line\nYou have no time\nMy persistence is outrageous\nYou’ll be mine, ’cause I’m contagious\nCome baby, come baby, get the feeling\nCome baby, come baby, get the meaning\nEla, ela, ela, la…\nI’ll make your heart go bang, bang\nCome baby, come baby, get the feeling\nCome baby, come baby, get the meaning\nEla, ela, ela, la…\nI’m the king of the night\nLet me show you tonight who I am\nEla, ela, ela, la…\n(Ela, ela, ela, ela, ela, la…)\n(Ela, ela, ela, ela, ela, la…)\nMysterious, delirious\nLet me be the key to passion\n“Ela” is the word for action\nCome baby, come baby, get the feeling\nCome baby, come baby, get the meaning\nEla, ela, ela, la…\nI’ll make your heart go bang, bang\nCome baby, come baby, get the feeling\nCome baby, come baby, get the meaning\nEla, ela, ela, la…\nI’m the king of the night\nLet me show you tonight who I am\n(Ela)\n(Come baby, come baby)\n(Come baby, come baby)\n(Come baby, come baby)\n(Come baby)\nCome baby, come baby, get the feeling\nYeah, come baby, come baby, get the meaning\nEla, ela, ela, la…\nI’ll make your heart go bang, bang\nCome baby, come baby, get the feeling\nYeah, come baby, come baby\nEla, ela, ela, la…\nI’m the king of the night\nLet me show you tonight who I am\nEla, ela, ela, la…\nI’m the king of the night\nLet me show you tonight who I am\nCome baby, come baby\n"
}
