{
  "song": "Autostop",
  "artist": "Anna Vissi & The Epikouri",
  "country": "Greece",
  "year": "1980",
  "lyrics": "\n\n\nGreek\nGreek script\nTranslation\n\n\n\nGreek\nAn thes ton kosmo na deis mazi mou xekina (Xekina)\nKai kane me autostop to gyro tis gis\nBoreis na pas opou thes, Evropi i Kina (Kina)\nKai «geia Athina» na peis kai opou vretheis\nKai ante, m’ autostop, autostop\nTaxidi m’ autostop, autostop, xekina gelasta\nAutostop, me autostop\nTa synora ein’ anoikta ki emeis mia syntrofia\nOi dromoi m’ autostop, autostop\nDikoi mas m’ autostop, autostop ki o kosmos mia stalia\nAutostop, me autostop, pantou tha pame\nGeia chara, me autostop, autostop\nPekino, Vladivostok, Parisi, Londino\nMe mia mikri sak-vouagiaz ton kosmo na deis\nStokcholmi, Kairo, Madriti, Romi, Verolino\nRouleta moiazei na ein’ o gyros tis gis\nKai ante, m’ autostop, autostop\nTaxidi m’ autostop, autostop, xekina gelasta\nAutostop, me autostop\nTa synora ein’ anoikta ki emeis mia syntrofia\nOi dromoi m’ autostop, autostop\nDikoi mas m’ autostop, autostop ki o kosmos mia stalia\nAutostop, me autostop, pantou tha pame\nGeia chara, me autostop, autostop\nKai ante, m’ autostop, hey\nLala lala lala…\nAutostop, me autostop, pantou tha pame\nGeia chara, me autostop, autostop\nAutostop, autostop\nAutostop\n\n"
}
