{
  "song": "Mou les",
  "artist": "Christie Stassinopoulou",
  "country": "Greece",
  "year": "1983",
  "lyrics": "\n\n\nGreek\nGreek script\nTranslation\n\n\n\nGreek\nMou les gia thalasses kai ploia, kai i kardia mou san pouli\nMesa ston korfo sou sopainei, ki opou ki an pas s’ akolouthei\nMesa ston korfo sou sopainei, ki opou ki an pas s’ akolouthei\nTha kleiso ola ta limania\nKai tous stathmous mi mou chatheis\nTo nou sou tha ton fylakiso\nNa papseis pia na nostalgeis\nTo nou sou tha ton fylakiso\nNa papseis pia na nostalgeis\nMou les gia trena pou olo fevgoun, kai gia tsinganous pou kinoun\nKi ego ta matia sou diavazo, na do pou trechoun pou gyrnoun\nKi ego ta matia sou diavazo, na do pou trechoun pou gyrnoun\nTha kleiso ola ta limania\nKai tous stathmous mi mou chatheis\nTo nou sou tha ton fylakiso\nNa papseis pia na nostalgeis\nTo nou sou tha ton fylakiso\nNa papseis pia na nostalgeis\nTha kleiso ola ta limania\nKai tous stathmous mi mou chatheis\nTo nou sou tha ton fylakiso\nNa papseis pia na nostalgeis\nTo nou sou tha ton fylakiso\nNa papseis pia na nostalgeis\n\n"
}
