{
  "song": "Anytime You Need",
  "artist": "Hayko",
  "country": "Armenia",
  "year": "2007",
  "lyrics": "\n\n\nEnglish/Armenian\nArmenian script\nTranslation\n\n\n\nEnglish/Armenian\nWhy? Baby, tell me why\nDoes someone always say goodbye?\nYou should never doubt, all I’ll ever do\nIs watch over you\nI only wanna guard\nEvery beat of your gentle heart\nLook and you will see\nYou can count on me, depend on me\nAnytime you need\nAny place you say\nAnything indeed\nAnyhow, any way\nI wanna be your friend\nDay by day to the very end\nIf you ever call crying with the blues\nI’m here for you\nAnytime you need\nAny place you say\nAnything indeed\nAnyhow, any way\nI’ll dry your tears when you cry\nAnd I need no reason why\nAnavart khosk’yer\nAnapak huyser\nArts’unk’ner u ser\nU haverzh k’yez het\nAnytime you need\n\n"
}
