{
  "song": "Un banc, un arbre, une rue",
  "artist": "Séverine",
  "country": "Monaco",
  "year": "1971",
  "lyrics": "\n\n\nFrench\nTranslation\n\n\n\nFrench\nOn a tous un banc, un arbre, une rue\nOù l’on a bercé nos rêves\nOn a tous un banc, un arbre, une rue\nUne enfance trop brève\nUn jour ou l’autre il faut partir\nPour se construire un avenir, un avenir\nEt c’est l’inoubliable instant\nOù l’on rend ses habits d’enfant, d’enfant\nChacun s’en va, rempli d’espoir\nSur le chemin qu’il s’est choisi, qu’il s’est choisi\nVers la richesse ou vers la gloire\nPourtant quelle que soit notre vie, notre vie\nOn a tous un banc, un arbre, une rue\nOù l’on a bercé nos rêves\nOn a tous un banc, un arbre, une rue\nUne enfance trop brève\nChacun, dans son coin d’horizon\nNe défend que ses ambitions, ses ambitions\nMais si nous ne partageons rien\nQue nous reste-t-il en commun, en commun?\nOn a tous un banc, un arbre, une rue\nOù l’on a bercé nos rêves\nOn a tous un banc, un arbre, une rue\nUne enfance trop brève\nLalala lala… lala lala lala…\nLalala lalala lala…\n\n"
}
