{
  "song": "Si tu aimes ma musique",
  "artist": "Stella",
  "country": "Belgium",
  "year": "1982",
  "lyrics": "\n\nFrench\nTranslation\n\n\n\nFrench\nC’est si doux le matin se lève en musique\nÇa rend un peu fou mais le réveil est plus euphorique\nElle te suit partout pendant toute la journée\nEt tous tes ennuis s’envolent aussitôt en fumée\nSi tu aimes ma musique chante-la avec moi\nSi tu veux danser personne ne t’empêchera\nN’est-elle pas magnifique? Chante à pleine voix\nFais qu’elle fasse vibrer le monde tout entier\nLa chanson, c’est ce qu’il y a de plus fantastique\nAussi nous chantons sur toutes les surfaces géographiques\nLe bonheur se trouve souvent dans une musique\nEt la bonne humeur, c’est comme une fleur vraiment magique\nSi tu aimes ma musique chante-la avec moi\nSi tu veux danser personne ne t’empêchera\nN’est-elle pas magnifique? Chante à pleine voix\nFais qu’elle fasse vibrer le monde tout entier\nSi tu aimes ma musique chante-la avec moi\nSi tu veux danser personne ne t’empêchera\nN’est-elle pas magnifique? Chante à pleine voix\nFais qu’elle fasse vibrer le monde tout entier\n\n"
}
