{
  "song": "Round and Round",
  "artist": "Tinkara Kovač",
  "country": "Slovenia",
  "year": "2014",
  "lyrics": "\n\n\nSlovene/English\nTranslation\n\n\n\nSlovene/English\nNegotovi, med svetovi\nKrog za krogom, ujeti v čas\nKo že veš za vse viharje si razigran\nA vendar si sam\nAnd now I’m gonna show you how to breathe\nI’m gonna show you how to live\n(I’m gonna hold your heart in hand)\nYeah I’m gonna make you understand\nYou don’t know, you don’t know, is it love, is it hate?\nWhat are you changing? (What are we doing?)\nYou don’t know, you don’t, but can you feel it inside?\nFeel the roses, feel the pride (Can you believe it?)\nRound and round again we…\nRound and round again we go… oh-oh…\nRound and round again we…\nRound and round again we go… oh-oh…\nIs a moment just a circle\nJust a song you play on repeat?\nIf we can’t change how we’re living\nIsn’t life just a lie that we feed?\nAnd now I’m gonna show you how to breathe\nI’m gonna show you how to live\n(I’m gonna hold your heart in hand)\nYeah I’m gonna make you understand\nYou don’t know, you don’t know, is it love, is it hate?\nWhat are you changing? (What are we doing?)\nYou don’t know, you don’t, but can you feel it inside?\nFeel the roses, feel the pride (Can you believe it?)\nRound and round again we…\nRound and round again we go… oh-oh…\nRound and round again we…\nRound and round again we go… oh-oh…\nKo nebo ne bo prekrilo najinih sanj\nPrerojena (Bova spoznala)\nKo nebo ne bo imelo pravih idej\nSpet bo najin čas (Da bi sijala)\nSpet vse bo isto, spet vse bo tisto\nKar je bilo, oh-oh…\nLe srce bo tisto ki ne bo več isto\nKar je bilo, vse kar je bilo\n\n"
}
