{
  "song": "No Dream Impossible",
  "artist": "Lindsay Dracass",
  "country": "United Kingdom",
  "year": "2001",
  "lyrics": "\nNo dream impossible\nNo dream impossible\nNo dream, no dream\n(Be strong, on and on)\n(Keep pushing, on and on)\n(Be strong, on and on)\n(Keep pushing, holding on)\nWe look for the highest\nWe follow the straightest road\nWe danced with the angels\nWhere heaven touches the end of the world\nWe look to the future\nWe reach for eternity\nThere in the distance\nEverything was so clear to me\nIf we keep holding on\nHave faith in ourselves\nBe strong, be free\nNo dream impossible\nNo dream impossible\nAs long as you’re living with hope in your heart\nIn dreams we’re untouchable\nForever invincible\nIf you believe with love in your heart\nThere’s no dream impossible\n(Hey you, have you got a dream?)\n(When you wake in the day)\n(Is it as bad as it seemed in the night?)\nHave you got a dream in ya heart?\n(When you’re fighting for your life) Hold on\n(Lotta strife) Ooh yeah\n(Don’t give up, when things gettin’ tough)\n(The city is a jungle and the strong survive)\nGotta be strong, keep holding on\n(Keep on, holding on) Keep strong\n(Keep pushing, on and on) You’re alive\n(Keep on, holding on)\nYou’re alive…\nNo dream impossible\nNo dream impossible\nAs long as you’re livin’ with hope in your heart\n(You’ve got to have hope in your heart)\nIn dreams we’re untouchable\n(In dreams we’re untouchable)\nForever invincible\nIf you believe with love in your heart\nThere’s no dream impossible\n(Keep on, holding on)\n(Keep pushing, on and on)\nThere’s no dream impossible\n"
}
