{
  "song": "Nous on veut des violons",
  "artist": "Morgane",
  "country": "Belgium",
  "year": "1992",
  "lyrics": "\n\nFrench\nTranslation\n\n\n\nFrench\nEn sweat, en pantalon, drôle de génération\nOn cache nos émotions sous la peau d’un blouson\nOui, mais sous l’apparence, mais derrière l’insouciance\nOn ne dit rien de nos blessures, ma génération assure\nEn rap et en funky, génération Gorby\nOn cache nos frissons sous des tonnes de béton\nMais cet air d’insouciance n’est rien qu’une apparence\nAu pays sans frontière, ma génération espère\nNous, on veut des violons et des statues de pierre\nMille ans de tradition, des sentiments dans l’air\nNous, on veut des violons, des oiseaux, des chimères\nEt des déclarations à ne plus toucher terre\nNous, on veut des violons\nNous, on n’a pas d’histoire, pas de passé, pas de mémoire\nMon cœur bat la chamade sous mon rire de parade\nJ’affiche l’indifférence, c’est rien qu’une apparence\nSous ses masques de couleur, ma génération a peur\nNous, on veut des violons et des statues de pierre\nMille ans de tradition, des sentiments dans l’air\nNous, on veut des violons, des oiseaux, des chimères\nEt des déclarations à ne plus toucher terre\nNous, on veut des violons\nNous, on veut des violons, on veut tout un orchestre\nEt puis des émotions, et puis des nuits d’ivresse\nNous, on veut des violons\nNous, on veut des violons et des statues de pierre\nMille ans de tradition, des sentiments dans l’air\nNous, on veut des violons, des oiseaux, des chimères\nEt des déclarations à ne plus toucher terre\nNous, on veut des violons\nNous, on veut des violons\nNous, on veut des violons\nNous, on veut des violons\n\n"
}
