{
  "song": "Alt det som ingen ser",
  "artist": "Lotte Nilsson & Kenny Lübcke",
  "country": "Denmark",
  "year": "1992",
  "lyrics": "\n\nDanish\nTranslation\n\n\n\nDanish\nMin fyr ble’ sur og han er gået hjem\nSå er du lis’som mig til fest alene?\nJeg kender ham, der’ ingen dør på klem\nSå’ du vel fri i nat sku’ jeg mene\nHør sig mig, tror du, at jeg’ en pige\nDer falder for enhver?\nDet vidste jeg, du ville si’\nSå hvorfor bli’r vi egentlig her?\nNår alt det som ingen ser\nDet har ingen ondt af, næ, tak, jeg bli’r tilbage\nAlt det som ingen ved\nDet ka’ ikke komme nogen andre vid, forstår du?\nJa, alt det som ingen ser\nDet har ingen ondt af, et frikvarter er OK\nHvis det’ til kærlighed\nOg hvis det kun er os der ved besked\nHva’ si’r du, syn’s du bare vi ska’ gå?\nGi’ mig en grund til at vi ikk’ sku’ gør’ det\nEt øjeblik, mens jeg ta’r frakken på\nDet’ er om at turde, mens man tør det\nVi ta’r en vogn, mens der er en at få\nUden at sanse tid og sted\nEr det ulovligt at satse på\nEn times tid til kærlighed?\nNår alt det som ingen ser\nDet har ingen ondt af, som denne her affære\nAlt det som ingen ved\nDet ka’ ikke komme de andre ved\nHva’ gør vi nu hvis nogen ser os gå fra festen?\nJo, for resten\nJeg har et trick der ikk’ blamer’ os:\nVi er gået, for du har fået\nEn enkelt tår mer’ end du sku’ ha’\nJa, den er go’ med dig\nNu finder jeg en dør at ta’\nSå ingen ser vi er på vej\nFor alt det som ingen ser\nDet har ingen ondt af, som denne her affære\nAlt det som ingen ved\nDet ka’ ikke komme de andre vid\nDu ved at alt det som ingen ser\nDet har ingen ondt af, et frikvarter er OK\nLynet ka’ let slå ned\nVi’ kun et sekund fra kærlighed\n\n"
}
