{
  "song": "Era",
  "artist": "Wess & Dori Ghezzi",
  "country": "Italy",
  "year": "1975",
  "lyrics": "\n\nItalian\nTranslation\n\n\n\nItalian\nDa un po’ di settimane in qua\nMi sento un’altra donna già\nChe vada tutto a rotoli\nOra, ora, ora\nAccanto a te, ci sono io\nAmore, sono tutto tuo\nE sembra quasi un secolo\nQuando far l’amore\nEra baciarsi al cinema\nEra la mia domenica\nEra trovare un angolo nascosto\nEra, era\nEra arrossire in pubblico (L’amore)\nEra parlarsi in codice (Di amore)\nEra rientrare prima della sera\nEra\nLe storie che inventavo ai miei\nLe amiche conosciute mai\nLa posta tra la biancheria\nEra ora, ora\nOra sfido il mondo io\nUn amore quando è mio, è mio\nE sembra quasi un secolo\nQuando far l’amore\nEra baciarsi al cinema\nEra la mia domenica\nEra trovare un angolo nascosto\nEra, era\nEra arrossire in pubblico (L’amore)\nEra parlarsi in codice (Di amore)\nEra rientrare prima della sera\nEra, era\nNa na na na na na na… (L’amore)\nNa na na na na na na… (Di amore)\nEra rientrare prima della sera\nEra, era\nNa na na na na na na…\nNa na na na na na na…\nNa na na na na na…\nEra, era, era\n\n"
}
