{
  "song": "Hold On Be Strong",
  "artist": "Maria Haukaas Storeng",
  "country": "Norway",
  "year": "2008",
  "lyrics": "\n\nLove can be hard sometimes\nYes, it can catch you off guard like bad crimes\nYes, it can make you depressed and angry\nMake you say: “Why me, why won’t anybody try me?”\nYou might be saying: “Ooh, I don’t wanna be lonely”\n“Ooh, I don’t wanna be by myself”\n“Ooh, don’t wanna be lonely”\n“Why ain’t anybody lovin’ me?”\nBut there’s always someone out there who’ll be there for you\nThere is always someone out there who’ll care for you\nThere’s always someone out there who’ll be true, true, true\nHold on, hold on, be strong\nLove can go away forever if you push it\nAnd you have to remember: don’t rush it\nIf it ain’t right, it is wrong\nAnd you’ll be crying: “Why me, why won’t anybody try me?”\nYou might be saying: “Ooh, I don’t wanna be lonely”\n“Ooh, I don’t wanna be by myself”\n“Ooh, don’t wanna be lonely, oh no no”\n“Why ain’t anybody lovin’ me?”\nNow, but there’s always someone out there who’ll be there for you\nAnd there’s always someone out there who’ll care for you\nThere’s always someone out there who’ll be true, true, true\nHold on, hold on, be strong\nAnd yes, there’s always someone out there who’ll be there for you\nAnd there’s always someone out there who’ll care for you\nThere’s always someone out there who’ll be true, true, true\nHold on, hold on, be strong\nHold on, hold on, be strong\nMy child, hold on, hold on, be strong\nMaria Haukaas Storeng’s Eurost☆r Page\n\n"
}
