{
  "song": "Dance with Me",
  "artist": "Zoli Ádok",
  "country": "Hungary",
  "year": "2009",
  "lyrics": "\n\nI see it in your eyes, you wanna dance with me tonight\nIt’s rainin’ on your body as you’re puttin’ up a fight\nThe way you’re moving, how you groove is somewhere out of sight\nYou know it’s only fair to tell you that you do it right\nNow with a little luck, I’m gonna meet you on the dance floor\nJust by the way you move you make me beg for more\nI’m burning with desire, it’s the night I’ve waited for\nDon’t you lose your emotion\nDon’t you be shy tonight\nLet the rhythm show you\nBaby, you can do it right\nAlright tonight\nCome on, dance with me, make me lose my way\nTake a chance with me, make my body sway\nIt’s an overload in a disco fantasy\nLet’s dance the night away\nJust yesterday we were on the floor\nLike somewhere in a movie or a club in Singapore\nThe lights are bright, the mood is raw\nAnd in the middle of the night, we dance till we get sore\nAnd in the middle of the night, I’ll meet you on the dancefloor\nGonna make it, move your body, beg for more\nWith a rhythm and a beat, I’ll rock you to the core\nDon’t you lose your emotion\nDon’t you be shy tonight\nLet the rhythm show you\nBaby, you can do it right\nAlright tonight\nCome on, dance with me, make me lose my way\nTake a chance with me, make my body sway\nIt’s an overload in a disco fantasy\nLet’s dance the night away\n(Dance with me)\n(Dance, dance, dance with me)\n(Dance with me)\nCome on, dance with me, make me lose my way\nTake a chance with me, make my body sway\nIt’s an overload in a disco fantasy\nLet’s dance the night away\nCome on, dance with me, make me lose my way\nTake a chance with me, make my body sway\nIt’s an overload in a disco fantasy\nLet’s dance the night away\n\n"
}
