{
  "song": "Zeit",
  "artist": "Bianca Shomburg",
  "country": "Germany",
  "year": "1997",
  "lyrics": "\n\nGerman\nTranslation\n\n\n\nGerman\nManchmal lief die Zeit mir durch die Hände\nManchmal wollt sie einfach nicht vergehen\nDoch die Zeit heilt viele Wunden\nUnd in manchen schweren Stunden\nTräumte ich die Zeit zurückzudrehen, denn\nZeit, Zeit, wo bleibt nur die Zeit?\nZeit, Zeit, wann ist es soweit?\nWer weiss was noch passiert?\nWer weiss wohin der Weg mich führt?\nSag, wo bist du?\nZeit, Zeit, was kommt in dieser Zeit\nNoch auf mich zu?\nIch hab um ein bisschen Glück gebetet\nUnd um die verlorne Zeit geweint\nDoch es konnt auf eine Frage\nMir keiner hier die Antwort sagen\nKönnen wir in Frieden glücklich sein? – Nein\nZeit, Zeit, wo bleibt nur die Zeit?\nZeit, Zeit, wann ist es soweit?\nWo werd ich morgen sein?\nBin ich am Ende doch allein?\nUnd wo bist du?\n(Zeit, Zeit, wo bleibt nur die Zeit?)\nWie schnell die Zeit vergeht\n(Zeit, Zeit, wann ist es soweit?)\nWie schnell der Wind sich dreht\nWer weiss was noch passiert?\nWer weiss wohin der Weg uns führt?\nSag, wo bist du?\nZeit, Zeit, ist der Weg auch weit\nIch brauch dazu nur ein wenig Zeit\n\n"
}
