{
  "song": "Fiumi di parole",
  "artist": "Jalisse",
  "country": "Italy",
  "year": "1997",
  "lyrics": "\n\nItalian\nTranslation\n\n\n\nItalian\nAh… ah… ah…\nMi aspetto mille scuse, come sempre da te\nSei un fiume di parole dove anneghi anche me\nChe bravo che sei, ma questo linguaggio da talk-show\nCosa c’entra con noi?\nProvo l’unico rimedio che adotto da un po’\nLa mia testa chiude l’audio, la storia la so\nSei fatto così, dovrei limitarmi oramai\nA dirti di sì\nFiumi di parole, fiumi di parole tra noi\nPrima o poi ci portano via\nTi darò il mio cuore, ti darò il mio cuore, se vuoi\nSe puoi, ora parla con lui\nOra parla con lui, ah…\nTu, che gridi in un dialetto, che non è più il mio\nIo, che perdo il tuo rispetto, sarebbe meglio un addio\nÈ come in un film, il classico film\nDove lei farà la pazzia\nFiumi di parole, fiumi di parole tra noi\nPrima o poi ci portano via\nTi darò il mio cuore, ti darò il mio cuore, se vuoi\nSe puoi, ora parla con lui\nVorrei fermare un’immagine\nSentirla entrare dentro di me\nUn tuo silenzio più complice\nVorrei…\nFiumi di parole, fiumi di parole tra noi\nPrima o poi ci portano via\nTi darò il mio cuore, ti darò il mio cuore, se vuoi\nSe puoi, ora parla con lui\nFiumi di parole, fiumi di parole tra noi\nPrima o poi ci portano via\nTi darò il mio cuore, ti darò il mio cuore, se vuoi\nSe puoi, ora parla con lui\nOra parla con lui\n(Fiumi di parole, fiumi di parole tra noi) Oh…\nTi darò il mio cuore, ti darò il mio cuore, se vuoi\nSe puoi, ora parla con lui\nFiumi di parole\n\n"
}
