{
  "song": "Wadde hadde dudde da?",
  "artist": "Stefan Raab",
  "country": "Germany",
  "year": "2000",
  "lyrics": "\n\nGerman/English\nTranslation\n\n\n\nGerman/English\nLadies and gentlemen, please\nPut your patsche hands together\nFor the sensational super sack of German television\nStefan Raab\nOh mein Gott, es gibt ihn wirklich!\nWow… er ging nach Amerika und sagte:\n“Wenn ich es dort schaffe”\n“Komm ich nie mehr nach Deutschland zurück”\nUnd heute Abend ist er wieder hier! Wow!\nWadde hadde dudde da?\nWadde hadde dudde da? Wadde hadde dudde da?\nWadde hadde dudde da? Wadde hadde dudde da?\nHadder denn da wat, un wenn ja, wat hadder da?\nHadder da watt glatt, oder hadder da wat Haar da?\nHadder da wat, wat sonst keiner hat?\nOder hadder dat auf dat, dat wadder da hat?\nDat wadder da da hat, dat hadder nu ma da\nDabei war ja gar nicht klar, dat dat dat da war\nWat dat war, dat war unklar\nUm darum, sammer domma, bidde, wadde hadde dudde da?\n(I am so curious, I just wanna know whatta you there have)\n(I am so curious, I just wanna know whatta you there have)\nWadde hadde dudde da?\nWadde hadde dudde da? Wadde hadde dudde da?\nWadde hadde dudde da? Wadde hadde dudde da?\nAha… wadde hadde dudde da?\nWadde dudde da da hat, hat ich schon vor ‘nem Jahr\nNee, nee, dat war weder dat, dat oder dat da\nWie, dat dat wat war?\nIch dachte dat dat dat war\nWat dat da war, dat is noch immer nich klar\nUn ob dat matt, platt, glatt, satt oder wat auch immer war\nDat dat wat war, un wenn, wat dat da war\nBidde, bidde, sammer domma, wadde hadde dudde da?\n(I am so curious, I just wanna know whatta you there have)\n(I am so curious, I just wanna know whatta you there have)\nWadde hadde dudde da?\nWadde hadde dudde da? Wadde hadde dudde da?\nWadde hadde dudde da? Wadde hadde dudde da?\nWadde hadde dudde da? Wadde hadde dudde da?\nWadde hadde dudde da? Wadde hadde dudde da?\nWadde hadde dudde da? Wadde hadde dudde da?\nOh mein Gott!\n\n"
}
